LICENSE
MANIFEST.in
README.md
setup.py
django_pipeline_node_sass.egg-info/PKG-INFO
django_pipeline_node_sass.egg-info/SOURCES.txt
django_pipeline_node_sass.egg-info/dependency_links.txt
django_pipeline_node_sass.egg-info/not-zip-safe
django_pipeline_node_sass.egg-info/top_level.txt
pipeline_node_sass/__init__.py
pipeline_node_sass/compiler.py