Metadata-Version: 1.1
Name: django-pipeline-node-sass
Version: 0.0.1
Summary: 
